MANIFEST.in
README.rst
setup.py
procrustes/__init__.py
procrustes/forms.py
procrustes/utils.py
procrustes/validators.py
procrustes/widgets.py
procrustes.egg-info/PKG-INFO
procrustes.egg-info/SOURCES.txt
procrustes.egg-info/dependency_links.txt
procrustes.egg-info/requires.txt
procrustes.egg-info/top_level.txt