Metadata-Version: 1.0
Name: procrustes
Version: 0.2.1
Summary: validation library
Home-page: https://github.com/Deepwalker/Procrustes/
Author: Svarga Developers
Author-email: svarga@librelist.com
License: BSD
Platform: UNKNOWN
Classifier: Intended Audience :: Developers
Classifier: License :: OSI Approved :: BSD License
Classifier: Operating System :: OS Independent
Classifier: Programming Language :: Python
